Workbook
Name プロジェクトコードと名称: プロジェクトコード!$F$3:$F$47
Name 科目一覧: 科目!$A$3:$G$204
Name 科目一覧2: 科目!$B$3:$G$161
Name 科目摘要: 科目!$A$3:$A$53
Name 詳細: 科目!$A$4:$A$8
Name 摘要: 科目!$A$3:$A$53
Name 部門: 部門!$A$3:$A$12

Sheet 経費（個人）精算書
A2: 経 費 精 算 書 （個人立替分）
AE3: ㈱リーディングソフト
A4: 決裁承認 | D4: 検印 | G4: 申請者 | J4: 部門 | N4: 社員番号 | R4: 氏名 | AE4: 作成日
AB5: 印 | AE5: =NOW() -> 45761.591
A9: 発生日 | G9: 摘要 | Y9: 金額（税込） | AF9: 財務経理部使用欄
G10: 用途
A11: 支払先名 | AF11: =IF(OR(J10="会議、業務打合せ時の昼食程度の飲食代",J10="取引先等に対する接待に要した飲食代"),IF(AD20<3001,"5020","5019"),IF(ISERROR(VLOOKUP(J10,科目一覧,3,FALSE)),"",VLOOKUP(J10,科目一覧,3,FALSE)))
G12: 摘要； | AF12: =IF(OR(J10="会議、業務打合せ時の昼食程度の飲食代",J10="取引先等に対する接待に要した飲食代"),IF(AD20<3001,"会議費","接待交際費"),IF(ISERROR(VLOOKUP(J10,科目一覧,4,FALSE)),"",VLOOKUP(J10,科目一覧,4,FALSE)))
AF13: =IF(J10="","",IF(AD20="",IF(ISERROR(VLOOKUP(J10,科目一覧,5,FALSE)),"",VLOOKUP(J10,科目一覧,5,FALSE)),IF(AD20<3000,"2",IF(AD20>5000,"1","2"))))
A14: 負担部門 | AF14: =IF(J10="","",IF(AD20="",IF(ISERROR(VLOOKUP(AF11&AF13,科目一覧2,5,FALSE)),"",VLOOKUP(AF11&AF13,科目一覧2,5,FALSE)),IF(AD20<3001,"飲食費",IF(AD20>5000,"飲食代","飲食代(損金算入)"))))
A16: プロジェクトコード、名称
G18: 相手先社名
A19: 稟議№、稟議承認日付 | G19: 相手先参加者名 | Y19: 人数 | AC19: 名 | AD19: 金額/人
G20: 当社参加者 | Y20: 人数 | AC20: 名 | AD20: =IF(AA20+AA19=0,"",Y10/(AA19+AA20))
A21: 発生日 | G21: 摘要 | Y21: 金額（税込） | AF21: 財務経理部使用欄
G22: 用途
A23: 支払先名 | AF23: =IF(OR(J22="会議、業務打合せ時の昼食程度の飲食代",J22="取引先等に対する接待に要した飲食代"),IF(AD32<3001,"5020","5019"),IF(ISERROR(VLOOKUP(J22,科目一覧,3,FALSE)),"",VLOOKUP(J22,科目一覧,3,FALSE)))
G24: 摘要； | AF24: =IF(OR(J22="会議、業務打合せ時の昼食程度の飲食代",J22="取引先等に対する接待に要した飲食代"),IF(AD32<3001,"会議費","接待交際費"),IF(ISERROR(VLOOKUP(J22,科目一覧,4,FALSE)),"",VLOOKUP(J22,科目一覧,4,FALSE)))
AF25: =IF(J22="","",IF(AD32="",IF(ISERROR(VLOOKUP(J22,科目一覧,5,FALSE)),"",VLOOKUP(J22,科目一覧,5,FALSE)),IF(AD32<3000,"2",IF(AD32>5000,"1","2"))))
A26: 負担部門 | AF26: =IF(J22="","",IF(AD32="",IF(ISERROR(VLOOKUP(AF23&AF25,科目一覧2,5,FALSE)),"",VLOOKUP(AF23&AF25,科目一覧2,5,FALSE)),IF(AD32<3001,"飲食費",IF(AD32>5000,"飲食代","飲食代(損金算入)"))))
A28: プロジェクトコード、名称
G30: 相手先社名
A31: 稟議№、稟議承認日付 | G31: 相手先参加者名 | Y31: 人数 | AC31: 名 | AD31: 金額/人
G32: 当社参加者 | Y32: 人数 | AC32: 名 | AD32: =IF(AA32+AA31=0,"",Y22/(AA31+AA32))
A33: 発生日 | G33: 摘要 | Y33: 金額（税込） | AF33: 財務経理部使用欄
G34: 用途
A35: 支払先名 | AF35: =IF(OR(J34="会議、業務打合せ時の昼食程度の飲食代",J34="取引先等に対する接待に要した飲食代"),IF(AD44<3001,"5020","5019"),IF(ISERROR(VLOOKUP(J34,科目一覧,3,FALSE)),"",VLOOKUP(J34,科目一覧,3,FALSE)))
G36: 摘要； | AF36: =IF(OR(J34="会議、業務打合せ時の昼食程度の飲食代",J34="取引先等に対する接待に要した飲食代"),IF(AD44<3001,"会議費","接待交際費"),IF(ISERROR(VLOOKUP(J34,科目一覧,4,FALSE)),"",VLOOKUP(J34,科目一覧,4,FALSE)))
AF37: =IF(J34="","",IF(AD44="",IF(ISERROR(VLOOKUP(J34,科目一覧,5,FALSE)),"",VLOOKUP(J34,科目一覧,5,FALSE)),IF(AD44<3000,"2",IF(AD44>5000,"1","2"))))
A38: 負担部門 | AF38: =IF(J34="","",IF(AD44="",IF(ISERROR(VLOOKUP(AF35&AF37,科目一覧2,5,FALSE)),"",VLOOKUP(AF35&AF37,科目一覧2,5,FALSE)),IF(AD44<3001,"飲食費",IF(AD44>5000,"飲食代","飲食代(損金算入)"))))
A40: プロジェクトコード、名称
G42: 相手先社名
A43: 稟議№、稟議承認日付 | G43: 相手先参加者名 | Y43: 人数 | AC43: 名 | AD43: 金額/人
G44: 当社参加者 | Y44: 人数 | AC44: 名 | AD44: =IF(AA44+AA43=0,"",Y34/(AA43+AA44))
Y46: 合計金額
Y47: =Y10+Y22+Y34 -> 0
A50: 管理部使用欄 | D50: 承認 | N50: 支払処理 | Y50: 伝票入力処理日
D51: 日付 | N51: 日付 | Y51: 日付
D53: 承認 | G53: 検印 | J53: 担当 | N53: 支払確認 | Q53: 担当 | Y53: 入力担当 | AB53: 伝票番号
C58: 相手科目 | G58: 現金 | M58: 当座預金 | U58: 未払金 | AA58: その他

Sheet 記入方法
B2: 記 入 要 領 ： 経 費 精 算 書 （個人立替分）
B4: 決裁承認 | E4: 検印 | H4: 申請者 | K4: 部門 | O4: 社員番号 | S4: 氏名 | AF4: 作成日
K5: 財務経理部 | O5: 330 | S5: ○○ ●● | AC5: 印 | AF5: =NOW() -> 45761.591
B9: 発生日 | H9: 摘要 | Z9: 金額（税込） | AG9: 財務経理部使用欄
B10: 39072 | H10: 用途 | K10: 会議費 | Z10: 18000
B11: 支払先名 | AG11: =IF(ISERROR(VLOOKUP(K10,科目一覧,3,FALSE)),"",VLOOKUP(K10,科目一覧,3,FALSE)) -> 020
B12: サンルートホテルズ | H12: 摘要； | AG12: =IF(ISERROR(VLOOKUP(K10,科目一覧,4,FALSE)),"",VLOOKUP(K10,科目一覧,4,FALSE)) -> 会議費
H13: 新日本監査法人と「内部統制報告書」対象の会社、重要な勘定科目に | AG13: =IF(K10="","",IF(VLOOKUP(K10,科目一覧,2,FALSE)="7180000001",IF(AE20<=5250,"0011","0001"),IF(ISERROR(VLOOKUP(K10,科目一覧,5,FALSE)),"",VLOOKUP(K10,科目一覧,5,FALSE)))) -> [製]会議費
B14: 負担部門 | H14: ついて打合せ | AG14: =IF(K10="","",IF(ISERROR(VLOOKUP(AG11&AG13,科目一覧2,5,FALSE)),"",VLOOKUP(AG11&AG13,科目一覧2,5,FALSE)))
B16: プロジェクトコード、名称
H18: 相手先社名 | M18: 新日本監査法人
B19: 稟議№、稟議承認日付 | H19: 相手先参加者名 | M19: ○○、○○、○○ | Z19: 人数 | AB19: 3 | AD19: 名 | AE19: 金額/人
H20: 当社参加者 | M20: ○○、○○、○○ | Z20: 人数 | AB20: 3 | AD20: 名 | AE20: =IF(AB20+AB19=0,"",Z10/(AB19+AB20)) -> 3000
B21: 発生日 | H21: 摘要 | Z21: 金額（税込） | AG21: 財務経理部使用欄
H22: 用途
B23: 支払先名 | AG23: =IF(ISERROR(VLOOKUP(K22,科目一覧,3,FALSE)),"",VLOOKUP(K22,科目一覧,3,FALSE))
H24: 摘要； | AG24: =IF(ISERROR(VLOOKUP(K22,科目一覧,4,FALSE)),"",VLOOKUP(K22,科目一覧,4,FALSE))
AG25: =IF(K22="","",IF(VLOOKUP(K22,科目一覧,2,FALSE)="7180000001",IF(AE32<=5250,"0011","0001"),IF(ISERROR(VLOOKUP(K22,科目一覧,5,FALSE)),"",VLOOKUP(K22,科目一覧,5,FALSE))))
B26: 負担部門 | AG26: =IF(K22="","",IF(ISERROR(VLOOKUP(AG23&AG25,科目一覧2,5,FALSE)),"",VLOOKUP(AG23&AG25,科目一覧2,5,FALSE)))
B29: 稟議№
H30: 相手先社名
B31: 稟議承認日付 | H31: 相手先参加者名 | Z31: 人数 | AD31: 名 | AE31: 金額/人
H32: 当社参加者 | Z32: 人数 | AD32: 名 | AE32: =IF(AB32+AB31=0,"",Z22/(AB31+AB32))
B33: 発生日 | H33: 摘要 | Z33: 金額（税込） | AG33: 財務経理部使用欄
H34: 用途
B35: 支払先名 | AG35: =IF(ISERROR(VLOOKUP(K34,科目一覧,3,FALSE)),"",VLOOKUP(K34,科目一覧,3,FALSE))
H36: 摘要； | AG36: =IF(ISERROR(VLOOKUP(K34,科目一覧,4,FALSE)),"",VLOOKUP(K34,科目一覧,4,FALSE))
AG37: =IF(K34="","",IF(VLOOKUP(K34,科目一覧,2,FALSE)="7180000001",IF(AE44<=5250,"0011","0001"),IF(ISERROR(VLOOKUP(K34,科目一覧,5,FALSE)),"",VLOOKUP(K34,科目一覧,5,FALSE))))
B38: 負担部門 | AG38: =IF(K34="","",IF(ISERROR(VLOOKUP(AG35&AG37,科目一覧2,5,FALSE)),"",VLOOKUP(AG35&AG37,科目一覧2,5,FALSE)))
B41: 稟議№
H42: 相手先社名
B43: 稟議承認日付 | H43: 相手先参加者名 | Z43: 人数 | AD43: 名 | AE43: 金額/人
H44: 当社参加者 | Z44: 人数 | AD44: 名 | AE44: =IF(AB44+AB43=0,"",Z34/(AB43+AB44))
Z46: 合計金額
Z47: =Z10+Z22+Z34 -> 18000
B50: 管理部使用欄 | E50: 承認 | O50: 支払処理 | Z50: 伝票入力処理日
E51: 日付 | O51: 日付 | Z51: 日付
E53: 承認 | H53: 検印 | K53: 担当 | O53: 支払確認 | R53: 担当 | Z53: 入力担当 | AC53: 伝票番号
D58: 相手科目 | H58: 現金 | N58: 当座預金 | V58: 未払金 | AB58: その他

Sheet 用途項目の選び方
B1: 用途項目の選び方
B2: 交際費 | C2: 取引先等に対する接待に要した飲食代
C3: 取引先等に対する接待に要した飲食代
C4: 慶弔花代、祝弔電等
C5: 取引先等に対するお祝い、見舞い等
C6: 取引先等に対するお中元、お歳暮代
C7: 慰安費
C8: お土産、ゴルフプレー代、商品券代等
B10: 会議費 | C10: 会議、業務打合せ時のお茶菓子代
C11: 会議、業務打合せ時の昼食程度の飲食代
C12: 会議会場使用料
C13: その他会議に要した費用
B15: 旅費交通費 | C15: バス・電車、タクシー、飛行機などの利用交通費
C16: ホテル代などの宿泊費
B18: 通信費 | C18: 電話料金使用料
C19: 国際電話料金使用料
C20: 携帯電話使用料
C21: 携帯電話（国際）使用料
C22: ポケットWIFI利用料金、ﾈｯﾄ接続料等
C23: 切手の購入、配達記録等の郵便代金
C24: もの発送料金（ゴルフバッグなど）
C25: その他、通信のためにかかった費用
B27: 消耗品費 | C27: 事務用品代、PC付属品、その他備品等の購入
B29: 図書費 | C29: 日経新聞等の購読料
C30: 参考書籍、雑誌等の購入費用
C31: 月刊誌等の雑誌購入費用
C32: 書統計資料、官報等の購入費用
B34: 福利厚生費＿レクレーション補助 | C34: レクレーション補助金の申請
B35: 福利厚生費＿社内福利厚生行事 | C35: 社内行事（社員旅行など）に関連する経費
B36: 福利厚生費＿健康診断 | C36: 健康診断料
B38: 他支払手数料 | C38: サービス利用料など
B41: 以下は主に管理部門で利用する用途項目
B42: 印紙税 | C42: 収入印紙の購入
B43: 他租税公課 | C43: 登記簿謄本、納税証明書など取得手数料等
B45: 水道光熱費 | C45: 寮などの光熱費
B46: 荷造運賃 | C46: 商品発送料金
B47: 諸会費 | C47: 会費支払
B48: 保険料 | C48: 保険料支払
B50: 立替金 | C50: 親会社などへの立替金

Sheet 集計シート
A1: 個人精算区分 | B1: 名前 | C1: 社員番号 | D1: 負担部門 | E1: 発生日 | F1: 開発区分 | G1: 勘定項目1 | H1: 勘定項目2 | I1: 勘定項目3 | J1: 勘定項目 | K1: 補助項目1 | L1: 補助項目2 | M1: 補助項目 | N1: 金額 | O1: 支払先 | P1: 税区分 | Q1: 摘要 | R1: プロジェクトコード:名称 | S1: ファイル名
A2: 経費立替 | B2: ='経費（個人）精算書'!R$5 -> 0 | C2: ='経費（個人）精算書'!N5 -> 0 | D2: =IF('経費（個人）精算書'!A15="",'経費（個人）精算書'!$J$5,'経費（個人）精算書'!A15) -> 0 | E2: ='経費（個人）精算書'!A10 -> 0 | F2: =IF(D2="管理部","",IF(D2="営業部","",IF(D2="取締役会","","製造部門"))) -> 製造部門 | G2: =IF('経費（個人）精算書'!J10="","",'経費（個人）精算書'!J10) | H2: =IF(G2="","",IF(ISNUMBER(FIND("＿",G2,1)),LEFT(G2,FIND("＿",G2,1)-1),G2)) | I2: =IF(H2="","",IF(ISNA(VLOOKUP(H2,科目!A:A,1,FALSE)),"その他",VLOOKUP(H2,科目!A:A,1,FALSE))) | J2: =IF(F2="製造部門",VLOOKUP(I2,科目!D:E,2,FALSE),I2) -> #N/A | K2: =IF(G2<>H2,RIGHT(G2,LEN(G2)-LEN(H2)-1),"") | L2: =IF(K2<>"",K2,IF(VLOOKUP(I2,科目!D:G,3,FALSE)="","",VLOOKUP(I2,科目!D:G,4,FALSE))) -> #N/A | M2: =IF(L2="社員名",B2,L2) -> #N/A | N2: ='経費（個人）精算書'!Y10 -> 0 | O2: ='経費（個人）精算書'!A12 -> 0 | P2: 課対仕入内10%適格 | Q2: =LEFTB('経費（個人）精算書'!I12&'経費（個人）精算書'!G13&'経費（個人）精算書'!G14&'経費（個人）精算書'!G15&'経費（個人）精算書'!G16&'経費（個人）精算書'!G17,64) | R2: ='経費（個人）精算書'!A17 | S2: =MID(CELL("filename"),FIND("[",CELL("filename"))+1,FIND("]",CELL("filename"))-FIND("[",CELL("filename"))-1) -> 精算書_集（個人経費立替）_氏名_YYYYMM.xlsx
A3: 経費立替 | B3: ='経費（個人）精算書'!R$5 -> 0 | C3: ='経費（個人）精算書'!N5 -> 0 | D3: =IF('経費（個人）精算書'!A27="",'経費（個人）精算書'!$J$5,'経費（個人）精算書'!A27) -> 0 | E3: ='経費（個人）精算書'!A22 -> 0 | F3: =IF(D3="管理部","",IF(D3="営業部","",IF(D3="取締役会","","製造部門"))) -> 製造部門 | G3: =IF('経費（個人）精算書'!J22="","",'経費（個人）精算書'!J22) | H3: =IF(G3="","",IF(ISNUMBER(FIND("＿",G3,1)),LEFT(G3,FIND("＿",G3,1)-1),G3)) | I3: =IF(H3="","",IF(ISNA(VLOOKUP(H3,科目!A:A,1,FALSE)),"その他",VLOOKUP(H3,科目!A:A,1,FALSE))) | J3: =IF(F3="製造部門",VLOOKUP(I3,科目!D:E,2,FALSE),I3) -> #N/A | K3: =IF(G3<>H3,RIGHT(G3,LEN(G3)-LEN(H3)-1),"") | L3: =IF(K3<>"",K3,IF(VLOOKUP(I3,科目!D:G,3,FALSE)="","",VLOOKUP(I3,科目!D:G,4,FALSE))) -> #N/A | M3: =IF(L3="社員名",B3,L3) -> #N/A | N3: ='経費（個人）精算書'!Y22 -> 0 | O3: ='経費（個人）精算書'!A24 -> 0 | P3: 課対仕入内10%適格 | Q3: =LEFTB('経費（個人）精算書'!I24&'経費（個人）精算書'!G25&'経費（個人）精算書'!G26&'経費（個人）精算書'!G27&'経費（個人）精算書'!G28&'経費（個人）精算書'!G29,64) | R3: ='経費（個人）精算書'!A29 -> 0 | S3: =MID(CELL("filename"),FIND("[",CELL("filename"))+1,FIND("]",CELL("filename"))-FIND("[",CELL("filename"))-1) -> 精算書_集（個人経費立替）_氏名_YYYYMM.xlsx
A4: 経費立替 | B4: ='経費（個人）精算書'!R$5 -> 0 | C4: ='経費（個人）精算書'!N5 -> 0 | D4: =IF('経費（個人）精算書'!A39="",'経費（個人）精算書'!$J$5,'経費（個人）精算書'!A39) -> 0 | E4: ='経費（個人）精算書'!A34 -> 0 | F4: =IF(D4="管理部","",IF(D4="営業部","",IF(D4="取締役会","","製造部門"))) -> 製造部門 | G4: =IF('経費（個人）精算書'!J34="","",'経費（個人）精算書'!J34) | H4: =IF(G4="","",IF(ISNUMBER(FIND("＿",G4,1)),LEFT(G4,FIND("＿",G4,1)-1),G4)) | I4: =IF(H4="","",IF(ISNA(VLOOKUP(H4,科目!A:A,1,FALSE)),"その他",VLOOKUP(H4,科目!A:A,1,FALSE))) | J4: =IF(F4="製造部門",VLOOKUP(I4,科目!D:E,2,FALSE),I4) -> #N/A | K4: =IF(G4<>H4,RIGHT(G4,LEN(G4)-LEN(H4)-1),"") | L4: =IF(K4<>"",K4,IF(VLOOKUP(I4,科目!D:G,3,FALSE)="","",VLOOKUP(I4,科目!D:G,4,FALSE))) -> #N/A | M4: =IF(L4="社員名",B4,L4) -> #N/A | N4: ='経費（個人）精算書'!Y34 -> 0 | O4: ='経費（個人）精算書'!A36 -> 0 | P4: 課対仕入内10%適格 | Q4: =LEFTB('経費（個人）精算書'!I36&'経費（個人）精算書'!G37&'経費（個人）精算書'!G38&'経費（個人）精算書'!G39&'経費（個人）精算書'!G40&'経費（個人）精算書'!G41,64) | R4: ='経費（個人）精算書'!A41 -> 0 | S4: =MID(CELL("filename"),FIND("[",CELL("filename"))+1,FIND("]",CELL("filename"))-FIND("[",CELL("filename"))-1) -> 精算書_集（個人経費立替）_氏名_YYYYMM.xlsx

Sheet 科目
A1: 科目摘要一覧
A2: 摘要 | C2: 勘定科目 | D2: 科目名 | E2: 製造科目名 | F2: 補助科目 | G2: 補助科目名
B3: =C3&F3
A4: =D4 -> 交際費 | C4: 010 | D4: 交際費 | E4: [製]交際費 | F4: 01 | G4: 社員名
A5: =D5 -> 会議費 | C5: 020 | D5: 会議費 | E5: [製]会議費 | F5: 01 | G5: 社員名
A6: =D6 -> 旅費交通費 | C6: 030 | D6: 旅費交通費 | E6: [製]旅費交通費 | F6: 01 | G6: 社員名
A7: =D7 -> 通信費 | C7: 040 | D7: 通信費 | E7: [製]通信費
A8: 消耗品費 | C8: 050 | D8: 消耗品費 | E8: [製]消耗品費
A9: =D9 -> 図書費 | C9: 060 | D9: 図書費 | E9: [製]図書費
A11: 福利厚生費＿レクレーション補助 | C11: 070 | D11: 福利厚生費 | E11: [製]福利厚生費 | F11: 01 | G11: レクレーション補助
A12: 福利厚生費＿社内福利厚生行事 | C12: 070 | D12: 福利厚生費 | E12: [製]福利厚生費 | F12: 02 | G12: 社内福利厚生行事
A13: 福利厚生費＿健康診断 | C13: 070 | D13: 福利厚生費 | E13: [製]福利厚生費 | F13: 03 | G13: 健康診断
A14: 福利厚生費 | C14: 070 | D14: 福利厚生費 | E14: [製]福利厚生費
A16: =D16 -> 他支払手数料 | C16: 080 | D16: 他支払手数料 | E16: [製]支払手数料
A18: =D18 -> 印紙税 | C18: 090 | D18: 印紙税 | E18: 印紙税
A19: =D19 -> 他租税公課 | C19: 100 | D19: 他租税公課 | E19: 他租税公課
A21: =D21 -> 水道光熱費 | C21: 110 | D21: 水道光熱費 | E21: [製]水道光熱費
A22: =D22 -> 荷造運賃 | C22: 120 | D22: 荷造運賃 | E22: [製]荷造運賃
A23: =D23 -> 諸会費 | C23: 130 | D23: 諸会費 | E23: [製]諸会費
A24: =D24 -> 保険料 | C24: 140 | D24: 保険料 | E24: [製]保険料
A26: 立替金＿LDNS | C26: 150 | D26: 立替金 | E26: 立替金 | F26: 01 | G26: LDNS
A27: 立替金 | C27: 150 | D27: 立替金 | E27: 立替金
A29: その他 | C29: 160 | D29: その他 | E29: その他
B38: =C38&F38
B39: =C39&F39
B41: =C41&F41
B42: =C42&F42
B43: =C43&F43
B44: =C44&F44
B45: =C45&F45
B46: =C46&F46
B47: =C47&F47
B48: =C48&F48
B49: =C49&F49
B50: =C50&F50
... B161: =C161&F161

Sheet 部門
A1: 部門名称一覧
A2: 部門 名前の定義：部門 | B2: 有効フラグ
B3: 1
A4: 取締役会 | B4: 1
A5: 営業部 | B5: 1
A6: 管理部 | B6: 1
A8: 開発本部 | B8: 1
A9: ソリューション開発部 | B9: 1
A10: プラットフォーム開発部 | B10: 1
A12: カスタマサポートエンジニアリング部 | B12: 1

Sheet プロジェクトコード
A1: プロジェクトコードと名称一覧 | C1: 1：オンサイト作業（現場）、2：一括開発/BSE・海外共同開発、3：保守、4：オフショア（離岸）
A2: プロジェクトコード 8桁 | B2: 名称 | C2: 有効フラグ | D2: 期間 FROM | E2: 期間 TO | F2: リスト表示用 名前の定義：プロジェクトコードと名称
F3: =IF(A3<>"",CONCATENATE(A3,"：",B3),"")
A4: SD0001 | B4: SD部門経費 | F4: =IF(A4<>"",CONCATENATE(A4,"：",B4),"") -> SD0001：SD部門経費
A5: PF0001 | B5: PF部門経費 | F5: =IF(A5<>"",CONCATENATE(A5,"：",B5),"") -> PF0001：PF部門経費
A6: CSE001 | B6: CSE部門経費 | F6: =IF(A6<>"",CONCATENATE(A6,"：",B6),"") -> CSE001：CSE部門経費
A7: KH0001 | B7: 開発本部部門経費 | F7: =IF(A7<>"",CONCATENATE(A7,"：",B7),"") -> KH0001：開発本部部門経費
F8: =IF(A8<>"",CONCATENATE(A8,"：",B8),"")
A9: BL0010 | B9: 先端技術開発室 | F9: =IF(A9<>"",CONCATENATE(A9,"：",B9),"") -> BL0010：先端技術開発室
A10: BL0021 | B10: 第一開発部 | F10: =IF(A10<>"",CONCATENATE(A10,"：",B10),"") -> BL0021：第一開発部
A11: BL0022 | B11: 第二開発部 | F11: =IF(A11<>"",CONCATENATE(A11,"：",B11),"") -> BL0022：第二開発部
A12: BL0023 | B12: 第三開発部 | F12: =IF(A12<>"",CONCATENATE(A12,"：",B12),"") -> BL0023：第三開発部
A13: BL0030 | B13: 情報システム部 | F13: =IF(A13<>"",CONCATENATE(A13,"：",B13),"") -> BL0030：情報システム部
A14: SB0011 | B14: IoT(龍海) | F14: =IF(A14<>"",CONCATENATE(A14,"：",B14),"") -> SB0011：IoT(龍海)
A15: SB0012 | B15: IoT(張慈勇) | F15: =IF(A15<>"",CONCATENATE(A15,"：",B15),"") -> SB0012：IoT(張慈勇)
A16: SB0021 | B16: ダンプネット企画ph | F16: =IF(A16<>"",CONCATENATE(A16,"：",B16),"") -> SB0021：ダンプネット企画ph
A17: SB0022 | B17: ダンプネット開発 | F17: =IF(A17<>"",CONCATENATE(A17,"：",B17),"") -> SB0022：ダンプネット開発
A18: SB0030 | B18: プラメBiz開発 | F18: =IF(A18<>"",CONCATENATE(A18,"：",B18),"") -> SB0030：プラメBiz開発
A19: SB0041 | B19: データプラットフォーム開発 | F19: =IF(A19<>"",CONCATENATE(A19,"：",B19),"") -> SB0041：データプラットフォーム開発
A20: SB0042 | B20: データプラットフォーム開発(南京) | F20: =IF(A20<>"",CONCATENATE(A20,"：",B20),"") -> SB0042：データプラットフォーム開発(南京)
... A43: SS0005 | B43: インフォート | F43: =IF(A43<>"",CONCATENATE(A43,"：",B43),"") -> SS0005：インフォート
F44: =IF(A44<>"",CONCATENATE(A44,"：",B44),"")
A45: KN0001 | B45: 管理部所管経費 | F45: =IF(A45<>"",CONCATENATE(A45,"：",B45),"") -> KN0001：管理部所管経費
F46: =IF(A46<>"",CONCATENATE(A46,"：",B46),"")
A47: AO0001 | B47: 青戸寮関連 | F47: =IF(A47<>"",CONCATENATE(A47,"：",B47),"") -> AO0001：青戸寮関連
